dprdct/__about__.py
dprdct/__init__.py
dprdct/client.py
dprdct/context.py
dprdct/main.py
dprdct/models.py
dprdct/utils.py
dprdct-0.0.1.dist-info/METADATA
dprdct-0.0.1.dist-info/WHEEL
dprdct-0.0.1.dist-info/licenses/LICENSE.txt
dprdct-0.0.1.dist-info/RECORD
