Metadata-Version: 2.4
Name: dprdct
Version: 0.0.1
Author-email: Ross Murphy <ross.a.murphy@gmail.com>
License-Expression: MIT
License-File: LICENSE.txt
Keywords: embeddings,large-language-models,llm,rag,retrieval,retrieval-augmented-generation,vector-database,vector-search,vector-store,vectors
Classifier: Development Status :: 4 - Beta
Classifier: Programming Language :: Python
Classifier: Programming Language :: Python :: 3.7
Classifier: Programming Language :: Python :: 3.8
Classifier: Programming Language :: Python :: 3.9
Classifier: Programming Language :: Python :: 3.10
Classifier: Programming Language :: Python :: 3.11
Classifier: Programming Language :: Python :: Implementation :: CPython
Classifier: Programming Language :: Python :: Implementation :: PyPy
Requires-Python: >=3.7
Requires-Dist: load-dotenv>=0.1.0
Requires-Dist: pydantic>=2.5.3
Requires-Dist: pytest>=7.4.4
Requires-Dist: requests
Requires-Dist: ruff>=0.11.8
Requires-Dist: tqdm
